toon_note/__init__.py
toon_note/_version.py
toon_note/labextension/package.json
toon_note/labextension/static/534.4250de0223a145e9529f.js
toon_note/labextension/static/568.bee592f3aa0d6df46656.js
toon_note/labextension/static/remoteEntry.739db775de519a04b277.js
toon_note/labextension/static/style.js
toon_note-0.1.0.data/data/share/jupyter/labextensions/toon_note/install.json
toon_note-0.1.0.data/data/share/jupyter/labextensions/toon_note/package.json
toon_note-0.1.0.data/data/share/jupyter/labextensions/toon_note/static/534.4250de0223a145e9529f.js
toon_note-0.1.0.data/data/share/jupyter/labextensions/toon_note/static/568.bee592f3aa0d6df46656.js
toon_note-0.1.0.data/data/share/jupyter/labextensions/toon_note/static/remoteEntry.739db775de519a04b277.js
toon_note-0.1.0.data/data/share/jupyter/labextensions/toon_note/static/style.js
toon_note-0.1.0.dist-info/LICENSE
toon_note-0.1.0.dist-info/METADATA
toon_note-0.1.0.dist-info/WHEEL
toon_note-0.1.0.dist-info/top_level.txt
toon_note-0.1.0.dist-info/RECORD
