Metadata-Version: 2.1
Name: toon-note
Version: 0.1.0
Summary: Extension for creating comics based on Daye Kang's ToonNote CHI2021 paper
Home-page: https://github.com/tho121/toon_note
Author: Tony Ho
Author-email: tho121.th@gmail.com
License: BSD-3-Clause
Keywords: Jupyter,JupyterLab,JupyterLab3
Platform: Linux
Platform: Mac OS X
Platform: Windows
Classifier: License :: OSI Approved :: BSD License
Classifier: Programming Language :: Python
Classifier: Programming Language :: Python :: 3
Classifier: Programming Language :: Python :: 3.6
Classifier: Programming Language :: Python :: 3.7
Classifier: Programming Language :: Python :: 3.8
Classifier: Programming Language :: Python :: 3.9
Classifier: Framework :: Jupyter
Requires-Python: >=3.6
Requires-Dist: jupyterlab (~=3.0)
Requires-Dist: jupyter-packaging (<2,~=0.9)
